MANIFEST.in
README.md
setup.py
centreseq/__init__.py
centreseq/centreseq_cli.py
centreseq/config.py
centreseq.egg-info/PKG-INFO
centreseq.egg-info/SOURCES.txt
centreseq.egg-info/dependency_links.txt
centreseq.egg-info/entry_points.txt
centreseq.egg-info/requires.txt
centreseq.egg-info/top_level.txt
centreseq/bin/__init__.py
centreseq/bin/core/__init__.py
centreseq/bin/core/accessories.py
centreseq/bin/core/alignments.py
centreseq/bin/core/generate_network_chart.py
centreseq/bin/core/mmseqs_wrapper.py
centreseq/bin/core/pairwise_comparisons.py
centreseq/bin/core/pick_best_nucleotide.py
centreseq/bin/core/pipelines.py
centreseq/bin/core/prokka_wrapper.py
centreseq/bin/core/sample_handling.py
centreseq/bin/core/speed_tests.py
centreseq/bin/core/summary.py
centreseq/bin/core/validate_clusters.py
centreseq/bin/helpers/__init__.py
centreseq/bin/helpers/extract_rep_multifasta.py
centreseq/bin/helpers/extract_subset.py
centreseq/bin/tree/__init__.py
centreseq/bin/tree/cluster_data_structures.py
centreseq/bin/tree/concatenate_sequences.py
centreseq/bin/tree/summary.py
centreseq/bin/tree/tree_pipeline.py
centreseq/bin/tree/wrappers.py
centreseq/bin/visualizations/__init__.py
centreseq/bin/visualizations/network_graph_template.html
centreseq/bin/visualizations/static/d3-simple-slider.js
centreseq/bin/visualizations/static/d3.v5.min.js