Metadata-Version: 2.1
Name: centreseq
Version: 0.2.3
Summary: Fast generation of a core genome among bacterial strains
Home-page: https://github.com/bfssi-forest-dussault/centreseq
Author: ['Forest Dussault', 'Adrian Verster', 'Nicholas Petronella']
Author-email: forest.dussault@canada.ca
License: UNKNOWN
Platform: UNKNOWN
Requires-Python: ~=3.6
